tro_utils/__init__.py
tro_utils/cli.py
tro_utils/default.jinja2
tro_utils/tro_utils.py
tro_utils-0.1.3.dist-info/licenses/AUTHORS.rst
tro_utils-0.1.3.dist-info/licenses/LICENSE
tro_utils-0.1.3.dist-info/METADATA
tro_utils-0.1.3.dist-info/WHEEL
tro_utils-0.1.3.dist-info/entry_points.txt
tro_utils-0.1.3.dist-info/top_level.txt
tro_utils-0.1.3.dist-info/RECORD
