Metadata-Version: 2.4
Name: tro-utils
Version: 0.1.3
Summary: Utilities for creating, editing and interacting with TROs
Author-email: Kacper Kowalik <xarthisius.kk@gmail.com>, Craig Willis <willis8@illinois.edu>
Maintainer-email: Kacper Kowalik <xarthisius.kk@gmail.com>
License: 
Classifier: Development Status :: 3 - Alpha
Classifier: Intended Audience :: Developers
Classifier: Topic :: Software Development :: Libraries
Classifier: License :: OSI Approved :: BSD License
Classifier: Programming Language :: Python :: 3
Classifier: Programming Language :: Python :: 3.10
Classifier: Programming Language :: Python :: 3.11
Classifier: Programming Language :: Python :: 3.12
Requires-Python: >=3.10
License-File: LICENSE
License-File: AUTHORS.rst
Requires-Dist: Click>=7.0
Requires-Dist: jinja2
Requires-Dist: requests
Requires-Dist: python-gnupg
Requires-Dist: python-magic
Requires-Dist: rfc3161ng
Requires-Dist: graphviz
Requires-Dist: rich
Provides-Extra: test
Requires-Dist: pytest>=6.2.4; extra == "test"
Requires-Dist: pytest-cov>=7.0.0; extra == "test"
Requires-Dist: coverage>=7.0; extra == "test"
Provides-Extra: dev
Requires-Dist: pytest>=6.2.4; extra == "dev"
Requires-Dist: pytest-cov>=7.0.0; extra == "dev"
Requires-Dist: coverage>=7.0; extra == "dev"
Requires-Dist: bump2version>=0.5.11; extra == "dev"
Requires-Dist: wheel>=0.33.6; extra == "dev"
Requires-Dist: watchdog>=0.9.0; extra == "dev"
Requires-Dist: flake8>=3.7.8; extra == "dev"
Requires-Dist: tox>=3.14.0; extra == "dev"
Requires-Dist: Sphinx>=1.8.5; extra == "dev"
Requires-Dist: twine>=1.14.0; extra == "dev"
Dynamic: license-file
